LICENSE
MANIFEST.in
README.md
setup.cfg
setup.py
ph4_runner.egg-info/PKG-INFO
ph4_runner.egg-info/SOURCES.txt
ph4_runner.egg-info/dependency_links.txt
ph4_runner.egg-info/requires.txt
ph4_runner.egg-info/top_level.txt
ph4runner/__init__.py